sanic_security/__init__.py
sanic_security/authentication.py
sanic_security/authorization.py
sanic_security/configuration.py
sanic_security/exceptions.py
sanic_security/models.py
sanic_security/oauth.py
sanic_security/utils.py
sanic_security/verification.py
sanic_security/test/__init__.py
sanic_security/test/server.py
sanic_security/test/tests.py
sanic_security-1.17.4.dist-info/licenses/LICENSE
sanic_security-1.17.4.dist-info/METADATA
sanic_security-1.17.4.dist-info/WHEEL
sanic_security-1.17.4.dist-info/top_level.txt
sanic_security-1.17.4.dist-info/RECORD
