Metadata-Version: 2.4
Name: sanic-security
Version: 1.17.4
Summary: An async security library for the Sanic framework.
Author-email: Aidan Stewart <me@na-stewart.com>
Project-URL: Documentation, https://security.na-stewart.com/
Project-URL: Repository, https://github.com/na-stewart/sanic-security
Keywords: security,authentication,authorization,verification,async,sanic
Classifier: Development Status :: 5 - Production/Stable
Classifier: Intended Audience :: Developers
Classifier: Topic :: Security
Classifier: License :: OSI Approved :: MIT License
Classifier: Programming Language :: Python
Requires-Python: >=3.8
License-File: LICENSE
Requires-Dist: tortoise-orm>=0.17.0
Requires-Dist: pyjwt>=1.7.0
Requires-Dist: captcha>=0.4
Requires-Dist: argon2-cffi>=20.1.0
Requires-Dist: sanic>=21.3.0
Provides-Extra: oauth
Requires-Dist: httpx-oauth>=0.16.1; extra == "oauth"
Provides-Extra: dev
Requires-Dist: httpx-oauth; extra == "dev"
Requires-Dist: black; extra == "dev"
Requires-Dist: blacken-docs; extra == "dev"
Requires-Dist: pdoc3; extra == "dev"
Requires-Dist: cryptography; extra == "dev"
Provides-Extra: crypto
Requires-Dist: cryptography>=3.3.1; extra == "crypto"
Dynamic: license-file
